{
  "snapshot_created_at": "2026-05-19T19:40:49.569155",
  "current_session_id": "eeed918f-e35c-4b8d-91bb-9d8c512fed2c",
  "recent_session_count": 2,
  "recent_sessions": [
    {
      "session_id": "eeed918f-e35c-4b8d-91bb-9d8c512fed2c",
      "timestamp": "2026-05-19T19:40:49.501527",
      "mode": "adaptive",
      "selected_sections": [
        6,
        8,
        9
      ],
      "score": 66.67,
      "total_questions": 6,
      "correct_count": 4,
      "wrong_count": 2,
      "adaptation_summary": "Adaptive run: prior history found. Focus more on weak topics and avoid excessive repetition of mastered questions.",
      "adaptation_payload": {
        "is_returning_run": true,
        "mode": "adaptive",
        "relevant_prior_session_count": 1,
        "weak_topics": [
          {
            "section_number": 8,
            "topic": "Safehouses",
            "attempts": 1,
            "wrong_count": 1,
            "correct_count": 0,
            "weakness_score": 1.0
          },
          {
            "section_number": 8,
            "topic": "Operational Territory",
            "attempts": 1,
            "wrong_count": 1,
            "correct_count": 0,
            "weakness_score": 1.0
          }
        ],
        "mastered_question_texts": [],
        "previous_wrong_question_texts": [
          "How often is safehouse provisioning audited?",
          "What is the primary operational base of the asset?"
        ],
        "summary": "Adaptive run: prior history found. Focus more on weak topics and avoid excessive repetition of mastered questions."
      },
      "questions_asked": [
        {
          "question_id": "e7d1f7d2-8c4d-4d6a-9d4c-8e5f6d7c8e9f",
          "section_number": 6,
          "topic": "Nordic Metahuman Operations Cell",
          "difficulty": "medium",
          "question": "How often are joint training rotations held for Nordic Metahuman Operations Cell?",
          "options": {
            "A": "Every 12 months",
            "B": "Every 18 months",
            "C": "Every 24 months",
            "D": "Every 6 months"
          },
          "user_answer": "B",
          "correct_answer": "B",
          "is_correct": true,
          "clarification": null,
          "adaptation_reason": "Prioritized weak topic: Safehouses",
          "source_chunk_ids": [
            "8605ceb7-739a-4ab7-a547-df12a785f39c"
          ]
        },
        {
          "question_id": "f1a2b3c4-d5e6-7f8g-9h0i-jk1l2m3n4",
          "section_number": 6,
          "topic": "European Metahuman Reserve",
          "difficulty": "medium",
          "question": "How often are reciprocal briefings held for European Metahuman Reserve?",
          "options": {
            "A": "Every 6 months",
            "B": "Every 12 months",
            "C": "Four times a year",
            "D": "Every 24 months"
          },
          "user_answer": "C",
          "correct_answer": "C",
          "is_correct": true,
          "clarification": null,
          "adaptation_reason": "Avoided close repeat of mastered question",
          "source_chunk_ids": [
            "8605ceb7-739a-4ab7-a547-df12a785f39c"
          ]
        },
        {
          "question_id": "f7c5a6b5-8d9e-4f6d-ba7e-1c2d3e4f5678",
          "section_number": 8,
          "topic": "Safehouses",
          "difficulty": "medium",
          "question": "How often is safehouse provisioning audited?",
          "options": {
            "A": "Daily",
            "B": "Weekly",
            "C": "Semi-annually",
            "D": "Monthly"
          },
          "user_answer": "A",
          "correct_answer": "C",
          "is_correct": false,
          "clarification": "Safehouse provisioning is audited semi-annually.",
          "adaptation_reason": "Prioritized weak topic: Safehouses",
          "source_chunk_ids": [
            "421ff765-5d8f-4b26-b568-e8e439c15860"
          ]
        },
        {
          "question_id": "c4b3a2b1-9e8d-4f6c-ba7d-1c2d3e4f5679",
          "section_number": 8,
          "topic": "Operational Territory",
          "difficulty": "medium",
          "question": "What is the primary operational base of the asset?",
          "options": {
            "A": "Cuartel Valpara\u00edso",
            "B": "PAMC South Cone Headquarters",
            "C": "Avenida Altamirano 1842",
            "D": "Valpara\u00edso"
          },
          "user_answer": "B",
          "correct_answer": "A",
          "is_correct": false,
          "clarification": "The asset's primary operational base is Cuartel Valpara\u00edso.",
          "adaptation_reason": "Prioritized weak topic: Operational Territory",
          "source_chunk_ids": [
            "11e8b047-54f6-42b9-a9b8-a0e6bbf19e09"
          ]
        },
        {
          "question_id": "9a1b2c3d-4e5f-6a7b-8c9d-e0f1g2h3i4",
          "section_number": 9,
          "topic": "Case File Format",
          "difficulty": "medium",
          "question": "What is the PAMC format for recording cases?",
          "options": {
            "A": "Case number (year-sequence)",
            "B": "Date (start\u2013end)",
            "C": "Location (city, province, country)",
            "D": "Outcome (Successful / Partial / Inconclusive /..."
          },
          "user_answer": "A",
          "correct_answer": "A",
          "is_correct": true,
          "clarification": null,
          "adaptation_reason": "Prioritized weak topic: Safehouses",
          "source_chunk_ids": [
            "2a89ad36-6d8e-4949-a65a-a0e94d21724a"
          ]
        },
        {
          "question_id": "9a1b2c3d-4e5f-6a7b-8c9d-e0f1g2h5",
          "section_number": 9,
          "topic": "Operational Success",
          "difficulty": "hard",
          "question": "What was the outcome of Case 2024-0202: Quebrantadero Showdown?",
          "options": {
            "A": "Successful",
            "B": "Partial",
            "C": "Inconclusive",
            "D": "Detained personnel led to seizure of USD $4.2 million in Concession assets"
          },
          "user_answer": "A",
          "correct_answer": "A",
          "is_correct": true,
          "clarification": null,
          "adaptation_reason": "Avoided close repeat of mastered question: Safehouse provisioning audit",
          "source_chunk_ids": [
            "77da46b4-29d5-4d6f-a117-d827cfd4b3f5"
          ]
        }
      ],
      "weak_topics": [
        {
          "section_number": 8,
          "topic": "Operational Territory",
          "attempts": 2,
          "wrong_count": 2,
          "correct_count": 0,
          "weakness_score": 1.0
        },
        {
          "section_number": 8,
          "topic": "Safehouses",
          "attempts": 2,
          "wrong_count": 2,
          "correct_count": 0,
          "weakness_score": 1.0
        },
        {
          "section_number": 9,
          "topic": "Operational Success",
          "attempts": 1,
          "wrong_count": 0,
          "correct_count": 1,
          "weakness_score": 0.0
        },
        {
          "section_number": 9,
          "topic": "Case File Format",
          "attempts": 1,
          "wrong_count": 0,
          "correct_count": 1,
          "weakness_score": 0.0
        },
        {
          "section_number": 6,
          "topic": "European Metahuman Reserve",
          "attempts": 1,
          "wrong_count": 0,
          "correct_count": 1,
          "weakness_score": 0.0
        },
        {
          "section_number": 6,
          "topic": "Nordic Metahuman Operations Cell",
          "attempts": 1,
          "wrong_count": 0,
          "correct_count": 1,
          "weakness_score": 0.0
        }
      ]
    },
    {
      "session_id": "2b942ff0-6b50-4fed-8d77-4dec7a5c2188",
      "timestamp": "2026-05-19T19:40:15.419661",
      "mode": "cold_start",
      "selected_sections": [
        5,
        8
      ],
      "score": 50.0,
      "total_questions": 4,
      "correct_count": 2,
      "wrong_count": 2,
      "adaptation_summary": "Cold-start run: no prior relevant history found.",
      "adaptation_payload": {
        "is_returning_run": false,
        "mode": "cold_start",
        "relevant_prior_session_count": 0,
        "weak_topics": [],
        "mastered_question_texts": [],
        "previous_wrong_question_texts": [],
        "summary": "Cold-start run: no prior relevant history found."
      },
      "questions_asked": [
        {
          "question_id": "1e5b2a3f-3c6b-4d7e-8e5b-4c3b2a1a3a1a",
          "section_number": 5,
          "topic": "Operational Tactics",
          "difficulty": "medium",
          "question": "What is the Doctrine of Sequential Suspension (DSS)?",
          "options": {
            "A": "A combat doctrine for Class A-1 operatives",
            "B": "An asset's formal combat doctrine",
            "C": "A PAMC-recognized doctrine for Class A-2 operatives",
            "D": "A tactical opportunity for civilian risk"
          },
          "user_answer": "C",
          "correct_answer": "C",
          "is_correct": true,
          "clarification": null,
          "adaptation_reason": "Prioritizing weak topics and avoiding close repeats of mastered questions.",
          "source_chunk_ids": [
            "68144153-edc2-4d07-b82f-9491716eed7b"
          ]
        },
        {
          "question_id": "2e5b2a3f-3c6b-4d7e-8e5b-4c3b2a1a3a1a",
          "section_number": 5,
          "topic": "Operational Tactics",
          "difficulty": "hard",
          "question": "What is the primary directive for acquiring targets?",
          "options": {
            "A": "Acquire targets only when extraction is mapped",
            "B": "Activate without verifying the contact-exclusion radius",
            "C": "Hold one activation in reserve until extraction",
            "D": "Engage Tier 4 only with two activations"
          },
          "user_answer": "A",
          "correct_answer": "A",
          "is_correct": true,
          "clarification": null,
          "adaptation_reason": "Prioritizing weak topics and avoiding close repeats of mastered questions.",
          "source_chunk_ids": [
            "c3f3119b-078d-4ece-9ce7-e165c5f4fc65"
          ]
        },
        {
          "question_id": "f8b4d8c3-5a7e-4f5c-8a4b-1a8c7b6c5d67",
          "section_number": 8,
          "topic": "Operational Territory",
          "difficulty": "medium",
          "question": "What is the primary operational base of the asset?",
          "options": {
            "A": "Cuartel Valpara\u00edso",
            "B": "PAMC South Cone Headquarters",
            "C": "Avenida Altamirano 1842",
            "D": "Valpara\u00edso"
          },
          "user_answer": "B",
          "correct_answer": "A",
          "is_correct": false,
          "clarification": "The primary operational base is Cuartel Valpara\u00edso.",
          "adaptation_reason": "Prioritizing weak topics and avoiding close repeats of mastered questions.",
          "source_chunk_ids": [
            "11e8b047-54f6-42b9-a9b8-a0e6bbf19e09"
          ]
        },
        {
          "question_id": "a9c2f1e4-6b7d-4d3c-ba4e-1c2f3d4e5f67",
          "section_number": 8,
          "topic": "Safehouses",
          "difficulty": "hard",
          "question": "How often is safehouse provisioning audited?",
          "options": {
            "A": "Annually",
            "B": "Semi-annually",
            "C": "Quarterly",
            "D": "Monthly"
          },
          "user_answer": "A",
          "correct_answer": "B",
          "is_correct": false,
          "clarification": "Safehouse provisioning is audited semi-annually.",
          "adaptation_reason": "Prioritizing weak topics and avoiding close repeats of mastered questions.",
          "source_chunk_ids": [
            "421ff765-5d8f-4b26-b568-e8e439c15860"
          ]
        }
      ],
      "weak_topics": [
        {
          "section_number": 8,
          "topic": "Operational Territory",
          "attempts": 2,
          "wrong_count": 2,
          "correct_count": 0,
          "weakness_score": 1.0
        },
        {
          "section_number": 8,
          "topic": "Safehouses",
          "attempts": 2,
          "wrong_count": 2,
          "correct_count": 0,
          "weakness_score": 1.0
        },
        {
          "section_number": 5,
          "topic": "Operational Tactics",
          "attempts": 2,
          "wrong_count": 0,
          "correct_count": 2,
          "weakness_score": 0.0
        }
      ]
    }
  ]
}